<MES>
  <MainWindow>
    <fontsize>36</fontsize>
    <nameDispLab>طائرة نفاثة ذكية متعددة الوظائف</nameDispLab>
    <fontsize>18</fontsize>
    <fileManageBut>إدارة الملفات</fileManageBut>
    <paraManageBut>إدارة البارامترات</paraManageBut>
    <startPrintBut>ابدأ الطباعة</startPrintBut>
    <closeBut>أغلق النظام</closeBut>
    <fontsize>12</fontsize>
    <No1Lab>خراطيش الحبر1</No1Lab>
    <No2Lab>2 خراطيش الحبر</No2Lab>
    <fontsize>20</fontsize>
    <speedMWLab>السرعة:</speedMWLab>
    <timeDelayMWLab>تأخير الوقت:</timeDelayMWLab>
    <dirMWLab>الاتجاه:</dirMWLab>
    <voltMWLab>الفولطية:</voltMWLab>
    <PWMWLab>النبض:</PWMWLab>
    <grayMWLab>الرمادي:</grayMWLab>
    <fileNmaeLab>اسم الملف:</fileNmaeLab>
    <countValMWLab>القيمة:</countValMWLab>
  </MainWindow>
  <FilemanageForm>
    <fontsize>20</fontsize>
    <editFileBut>تحرير الوثائق</editFileBut>
    <exitBut>الانسحاب</exitBut>
    <manageFileBut>وثائق الإدارة</manageFileBut>
  </FilemanageForm>
  <FileEditChild>
    <fontsize>16</fontsize>
    <fontTypeTextLab>الخط</fontTypeTextLab>
    <fontSizeTextLab>ب -ا -</fontSizeTextLab>
    <variableTextBut>المتغيرة</variableTextBut>
    <newTextBut>الجديدة</newTextBut>
    <delBut>حذف</delBut>
    <saveBut>حفظ</saveBut>
    <saveasBut>الباقي</saveasBut>
    <rotateTextLab>تدور</rotateTextLab>
    <internalTextLab>بين</internalTextLab>
    <pixelLab>بكسل</pixelLab>
    <moveSpeedLab>تتحرك بسرعة ضعف</moveSpeedLab>

    <addTimeBut>إضافة</addTimeBut>
    <refreshTimeBut>تحديث</refreshTimeBut>
    <newTimeBut>الجديدة</newTimeBut>
    <fontTypeTimeLab>الخط</fontTypeTimeLab>
    <fontTypeTimeLab_3>لتحويل</fontTypeTimeLab_3>
    <fontTypeTimeLab_4>الانحراف</fontTypeTimeLab_4>
    <fontTypeTimeLab_5>وحدة تحويل مسار</fontTypeTimeLab_5>
    <fontTypeTimeLab_6>معاينة</fontTypeTimeLab_6>
    <fontTypeTimeLab_7>التاريخ/الوقت</fontTypeTimeLab_7>
    
    <initialValSerialLab>العتبة </initialValSerialLab>
    <termValSerialLab>قيمة الإنهاء</termValSerialLab>
    <startValSerialLab>بداية</startValSerialLab>
    <stepLenSerialLab>خطوة أطوال</stepLenSerialLab>
    <reptCountSerialLab>كرر العد</reptCountSerialLab>
    <digitSerialLab>أرقام</digitSerialLab>
    <counterSerialLab>عداد</counterSerialLab>
    <fontTypeSerialLab>الخط</fontTypeSerialLab>
    <formatSerialLab>شكل</formatSerialLab>
    <newSerialBut>الجديدة</newSerialBut>
    
    <heightBmpLab>عالية</heightBmpLab>
    <widthBmpLab>عرض</widthBmpLab>
    <reverseBmpCheckBox>عكس الألوان</reverseBmpCheckBox>
    <selBmpBut>إختر الرسومات</selBmpBut>
    <newBmpBut>الجديدة</newBmpBut>
    <proportionBmpCheckBox>الإنتظار</proportionBmpCheckBox>

    <typeBarCodeLab>أنواع</typeBarCodeLab>
    <zoomBarCodeLab>التكبير</zoomBarCodeLab>
    <heightBarCodeLab>عالية</heightBarCodeLab>
    <variableBarCodeBut>المتغيرة</variableBarCodeBut>
    <newBarCodeBut>الجديدة</newBarCodeBut>
    <typeBarCodeLab_2>نوع الإطار</typeBarCodeLab_2>
    <zoomBarCodeLab_2>عرض فارغ</zoomBarCodeLab_2>

    <showNumCheckBox>أرني الأرقام</showNumCheckBox>
    <sideLenQRLab>طول</sideLenQRLab>
    <reverseCheckBox>ألوان مختلفة</reverseCheckBox>
    <variableQRBut>المتغيرة</variableQRBut>
    <newQRBut>الجديدة</newQRBut>

    <sideLenDMLab>أنواع</sideLenDMLab>
    <variableDMBut>المتغيرة</variableDMBut>
    <newDMBut>الجديدة</newDMBut>
    <fontsize>12</fontsize>
    <typeTab>الوثائق#الوقت#رقم تسلسلي#الصورة#شفرة الخطوط المتوازية#رمز الاستجابة السريعة#dm، ياردة</typeTab>
  </FileEditChild>
  <FileManageChild>
    <fontsize>18</fontsize>
    <localFileBut>الوثائق المحلية</localFileBut>
    <UdiskFileBut>ملف قرص U</UdiskFileBut>
    <loadSeleFileBut>تحميل ملفّ مُنتقى</loadSeleFileBut>
    <editSeleFileBut>تحرير مُنتقى ملف</editSeleFileBut>
    <delSeleFileBut>احذف مُنتقى ملف</delSeleFileBut>
    <copyFile2localBut>نسخ محلية</copyFile2localBut>
    <OKFileNameBut>تحديد</OKFileNameBut>
  </FileManageChild>
  <ParamSettingForm>
    <fontsize>18</fontsize>
    <printSettingBut>إعداد الطباعة</printSettingBut>
    <sysSettingBut>إعدادات النظام</sysSettingBut>
    <countSettingBut>إعداد العد</countSettingBut>
    <aboutMacBut>عن الآلة</aboutMacBut>
    <paraExitBut>الانسحاب</paraExitBut>
    <fontsize>20</fontsize>
    <resetBut>الاستبدال</resetBut>
    <savePrintSetBut>حفظ</savePrintSetBut>
  </ParamSettingForm>
  <printSetting>
    <fontsize>15</fontsize>
     <printSpeedLab>سرعة الطباعة M/MIN.</printSpeedLab>
     <printDelayLab>طباعة تأخير M.</printDelayLab>
     <synFrequencyLab>تردد متزامن</synFrequencyLab>
     <printGrayLab>طباعة الرمادي</printGrayLab>
     <trigLab>طريقة الإطلاق</trigLab>
     <inkjetLab>طريقة رش الحبر</inkjetLab>
     <printDirLab>اتجاه الطباعة</printDirLab>
     <synWheelCheckBox>مكّن التزامن</synWheelCheckBox>
     <voiceCheckBox>الصوت</voiceCheckBox>
     <trigComBox>العين الخارجية#تلقائيا#ضوئي#جهاز التشفير#شفرة كهروضوئية#الضوء</trigComBox>
     <inkjetComBox>اليسار رش#اليمين رش</inkjetComBox>
     <printDirComBox>تتحرك#العكسية</printDirComBox>

     <repetePrintCheckBox>كرر الطباعة</repetePrintCheckBox>
     <repeteLab>مرات متكررة</repeteLab>
     <repeteDelayLab>كرر تأخير M.</repeteDelayLab>

     <inkTypeLab>نوع الحبر</inkTypeLab>
     <adaptParaCheckBox>معايير التكيف الذاتي</adaptParaCheckBox> 
     <inkVoltLab>الفولطية</inkVoltLab>
     <PWLab>عرض النبض</PWLab>
     <nozzleSelLab>اختيار فوهة</nozzleSelLab>
     <offsetLab>تحويل مسار</offsetLab>
     <flashSprayLab>فلاش إعدادات</flashSprayLab>
     <flashSprayCheckBox>شيم رش</flashSprayCheckBox>
     <flashSprayInternalLab>المباعدة س</flashSprayInternalLab>
     <flashSprayTimesLab>عدد</flashSprayTimesLab>
     <printSetTabWid>أسلوب الطباعة#إعدادات متقدمة#إعداد المحرك#أضواء UV إعدادات</printSetTabWid>
  </printSetting>
  <sysSetting>
     <fontsize>18</fontsize>
     <sysTimeSetLab>وقت النظام</sysTimeSetLab>
     <backLightLab>ضوء الظهر</backLightLab>
     <sysLanguageLab>لغة النظام</sysLanguageLab>
  </sysSetting>
  <countSetting>
      <fontsize>18</fontsize>
      <counterOneLab>العداد 1.</counterOneLab>
      <currentVal1Lab>القيمة الحالية</currentVal1Lab>
      <initialVal1Lab>القيمة الأولية</initialVal1Lab>
      <repeteTime1Lab>مرات متكررة</repeteTime1Lab>
      <stepVal1Lab>خطوة للأمام</stepVal1Lab>
      <maxVal1Lab>الأقصى</maxVal1Lab>
      <counterTwoLab>العداد 2.</counterTwoLab>
      <currentVal2Lab>القيمة الحالية</currentVal2Lab>
      <initialVal2Lab>القيمة الأولية</initialVal2Lab>
      <repeteTime2Lab>مرات متكررة</repeteTime2Lab>
      <stepVal2Lab>خطوة للأمام</stepVal2Lab>
      <maxVal2Lab>الأقصى</maxVal2Lab>
      <printTimeLab>عدد الطباعة</printTimeLab>
  </countSetting>
</MES>
















